pipgrip/__init__.py
pipgrip/_repo_version.py
pipgrip/cli.py
pipgrip/compat.py
pipgrip/package_source.py
pipgrip/pipper.py
pipgrip/libs/__init__.py
pipgrip/libs/mixology/__init__.py
pipgrip/libs/mixology/_compat.py
pipgrip/libs/mixology/assignment.py
pipgrip/libs/mixology/constraint.py
pipgrip/libs/mixology/failure.py
pipgrip/libs/mixology/incompatibility.py
pipgrip/libs/mixology/incompatibility_cause.py
pipgrip/libs/mixology/package.py
pipgrip/libs/mixology/package_source.py
pipgrip/libs/mixology/partial_solution.py
pipgrip/libs/mixology/range.py
pipgrip/libs/mixology/result.py
pipgrip/libs/mixology/set_relation.py
pipgrip/libs/mixology/term.py
pipgrip/libs/mixology/union.py
pipgrip/libs/mixology/version_solver.py
pipgrip/libs/semver/__init__.py
pipgrip/libs/semver/empty_constraint.py
pipgrip/libs/semver/exceptions.py
pipgrip/libs/semver/patterns.py
pipgrip/libs/semver/version.py
pipgrip/libs/semver/version_constraint.py
pipgrip/libs/semver/version_range.py
pipgrip/libs/semver/version_union.py
pipgrip-0.11.1.dist-info/licenses/LICENSE
pipgrip-0.11.1.dist-info/METADATA
pipgrip-0.11.1.dist-info/WHEEL
pipgrip-0.11.1.dist-info/entry_points.txt
pipgrip-0.11.1.dist-info/top_level.txt
pipgrip-0.11.1.dist-info/RECORD
