Metadata-Version: 2.4
Name: pipgrip
Version: 0.11.1
Summary: Lightweight pip dependency resolver with deptree preview functionality based on the PubGrub algorithm
Home-page: https://github.com/ddelange/pipgrip
Author: ddelange
Author-email: ddelange@delange.dev
License: BSD-3-Clause
Keywords: pure-Python pip exhaustive package dependency version conflict resolver PyPI PubGrub pipdeptree
Classifier: Development Status :: 5 - Production/Stable
Classifier: Environment :: Console
Classifier: Intended Audience :: Developers
Classifier: License :: OSI Approved :: BSD License
Classifier: Operating System :: OS Independent
Classifier: Programming Language :: Python
Classifier: Programming Language :: Python :: 2
Classifier: Programming Language :: Python :: 2.7
Classifier: Programming Language :: Python :: 3
Classifier: Programming Language :: Python :: 3.5
Classifier: Programming Language :: Python :: 3.6
Classifier: Programming Language :: Python :: 3.7
Classifier: Programming Language :: Python :: 3.8
Classifier: Programming Language :: Python :: 3.9
Classifier: Programming Language :: Python :: 3.10
Classifier: Programming Language :: Python :: 3.11
Classifier: Programming Language :: Python :: 3.12
Classifier: Topic :: Software Development :: Libraries :: Python Modules
Classifier: Topic :: System :: Archiving :: Packaging
Classifier: Topic :: System :: Systems Administration
Classifier: Topic :: System :: Installation/Setup
Classifier: Topic :: Utilities
Requires-Python: >=2.7, !=3.0.*, !=3.1.*, !=3.2.*, !=3.3.*, !=3.4.*
License-File: LICENSE
Requires-Dist: anytree>=2.4.1
Requires-Dist: click>=7
Requires-Dist: packaging>=17
Requires-Dist: setuptools<81,>=38.3
Requires-Dist: wheel
Requires-Dist: pip>=22.2; python_version > "3.6"
Requires-Dist: pip>=7.1.0; python_version <= "3.6"
Requires-Dist: pkginfo<1.8,>=1.4.2; python_version <= "3.6"
Requires-Dist: enum34; python_version == "2.7"
Requires-Dist: typing; python_version == "2.7"
Dynamic: author
Dynamic: author-email
Dynamic: classifier
Dynamic: description
Dynamic: description-content-type
Dynamic: home-page
Dynamic: keywords
Dynamic: license
Dynamic: license-file
Dynamic: requires-dist
Dynamic: requires-python
Dynamic: summary
